ltpackagetemplate/__init__.py
ltpackagetemplate/__main__.py
ltpackagetemplate/exector.py
ltpackagetemplate/utils/__init__.py
ltpackagetemplate/utils/print_with_color.py
ltpackagetemplate-0.0.1.2.dist-info/METADATA
ltpackagetemplate-0.0.1.2.dist-info/WHEEL
ltpackagetemplate-0.0.1.2.dist-info/top_level.txt
ltpackagetemplate-0.0.1.2.dist-info/RECORD
