Metadata-Version: 2.1
Name: ltpackagetemplate
Version: 0.0.1.2
Summary: package template
Home-page: UNKNOWN
Author: LiTing
Author-email: UNKNOWN
License: MIT
Keywords: package template
Platform: UNKNOWN
Classifier: License :: OSI Approved :: MIT License
Classifier: Operating System :: OS Independent
Classifier: Programming Language :: Python :: 3
Classifier: Programming Language :: Python :: 3.6
Classifier: Programming Language :: Python :: 3.7
